asimov/__init__.py
asimov/analysis.py
asimov/asimov.conf
asimov/auth.py
asimov/condor.py
asimov/database.py
asimov/event.py
asimov/git.py
asimov/ini.py
asimov/ledger.py
asimov/locutus.py
asimov/logging.py
asimov/mattermost.py
asimov/olivaw.py
asimov/pipeline.py
asimov/review.py
asimov/storage.py
asimov/testing.py
asimov/utils.py
asimov/cli/__init__.py
asimov/cli/application.py
asimov/cli/configuration.py
asimov/cli/data.py
asimov/cli/event.py
asimov/cli/ledger.py
asimov/cli/manage.py
asimov/cli/monitor.py
asimov/cli/production.py
asimov/cli/project.py
asimov/cli/report.py
asimov/cli/review.py
asimov/cli/report-theme/body.html
asimov/cli/report-theme/footer.html
asimov/cli/report-theme/head.html
asimov/cli/report-theme/header.html
asimov/configs/README.rst
asimov/configs/bayeswave.ini
asimov/configs/bilby.ini
asimov/configs/lalinference.ini
asimov/configs/pesummary.ini
asimov/configs/rift.ini
asimov/pipelines/__init__.py
asimov/pipelines/bayeswave.py
asimov/pipelines/bilby.py
asimov/pipelines/lalinference.py
asimov/pipelines/pesummary.py
asimov/pipelines/rift.py
asimov/report-theme/body.html
asimov/report-theme/footer.html
asimov/report-theme/head.html
asimov/report-theme/header.html
asimov-0.6.1.dist-info/LICENSE
asimov-0.6.1.dist-info/METADATA
asimov-0.6.1.dist-info/WHEEL
asimov-0.6.1.dist-info/entry_points.txt
asimov-0.6.1.dist-info/top_level.txt
asimov-0.6.1.dist-info/zip-safe
asimov-0.6.1.dist-info/RECORD
