Metadata-Version: 2.1
Name: asimov
Version: 0.6.1
Summary: A Python package for managing and interacting with data analysis jobs.
Home-page: https://git.ligo.org/asimov/asimov
Author: Daniel Williams
Author-email: daniel.williams@ligo.org
License: MIT license
Keywords: pe,ligo,asimov
Classifier: Development Status :: 5 - Production/Stable
Classifier: Environment :: Console
Classifier: Intended Audience :: Science/Research
Classifier: Topic :: Scientific/Engineering :: Astronomy
Classifier: Topic :: Scientific/Engineering :: Information Analysis
Classifier: License :: OSI Approved :: ISC License (ISCL)
Classifier: Natural Language :: English
Classifier: Programming Language :: Python :: 3
Classifier: Programming Language :: Python :: 3.7
Classifier: Programming Language :: Python :: 3.8
Classifier: Programming Language :: Python :: 3.9
Classifier: Programming Language :: Python :: 3.10
License-File: LICENSE
Requires-Dist: click
Requires-Dist: gitpython
Requires-Dist: htcondor
Requires-Dist: ligo-gracedb
Requires-Dist: liquidpy
Requires-Dist: networkx
Requires-Dist: numpy
Requires-Dist: otter-report >=0.3.3
Requires-Dist: python-gitlab
Requires-Dist: pytz
Requires-Dist: pyyaml
Requires-Dist: requests
Requires-Dist: gwpy
Requires-Dist: lscsoft-glue >=2.0.0
Requires-Dist: igwn-auth-utils >=0.2.1
Requires-Dist: flask
Requires-Dist: tinydb
Requires-Dist: pillow >=10.2.0
